{
	"configurations" : 
	[
		{
			"directories" : 
			[
				{
					"build" : ".",
					"childIndexes" : 
					[
						1,
						2
					],
					"hasInstallRule" : true,
					"jsonFile" : "directory-.-Debug-d0094a50bb2071803777.json",
					"minimumCMakeVersion" : 
					{
						"string" : "3.30"
					},
					"projectIndex" : 0,
					"source" : ".",
					"targetIndexes" : 
					[
						2
					]
				},
				{
					"build" : "_deps/doctest-build",
					"hasInstallRule" : true,
					"jsonFile" : "directory-_deps.doctest-build-Debug-b7f342a48ce67cb1af12.json",
					"minimumCMakeVersion" : 
					{
						"string" : "3.5"
					},
					"parentIndex" : 0,
					"projectIndex" : 1,
					"source" : "cmake-build-debug/_deps/doctest-src",
					"targetIndexes" : 
					[
						0
					]
				},
				{
					"build" : "examples",
					"jsonFile" : "directory-examples-Debug-2e8964349ffea94e1580.json",
					"minimumCMakeVersion" : 
					{
						"string" : "3.30"
					},
					"parentIndex" : 0,
					"projectIndex" : 0,
					"source" : "examples",
					"targetIndexes" : 
					[
						1
					]
				}
			],
			"name" : "Debug",
			"projects" : 
			[
				{
					"childIndexes" : 
					[
						1
					],
					"directoryIndexes" : 
					[
						0,
						2
					],
					"name" : "stochastic",
					"targetIndexes" : 
					[
						1,
						2
					]
				},
				{
					"directoryIndexes" : 
					[
						1
					],
					"name" : "doctest",
					"parentIndex" : 0,
					"targetIndexes" : 
					[
						0
					]
				}
			],
			"targets" : 
			[
				{
					"directoryIndex" : 1,
					"id" : "doctest_with_main::@de8c2d1415f8a28c2e63",
					"jsonFile" : "target-doctest_with_main-Debug-f3de611cdd9acf754b0d.json",
					"name" : "doctest_with_main",
					"projectIndex" : 1
				},
				{
					"directoryIndex" : 2,
					"id" : "example1::@714eac15f71a94114fdf",
					"jsonFile" : "target-example1-Debug-db7eaecaaeeaf1164197.json",
					"name" : "example1",
					"projectIndex" : 0
				},
				{
					"directoryIndex" : 0,
					"id" : "stochastic::@6890427a1f51a3e7e1df",
					"jsonFile" : "target-stochastic-Debug-b90bcd2260737b33a6eb.json",
					"name" : "stochastic",
					"projectIndex" : 0
				}
			]
		}
	],
	"kind" : "codemodel",
	"paths" : 
	{
		"build" : "C:/Users/Jonathan/Documents/Programmering/8.semester/stochastic/cmake-build-debug",
		"source" : "C:/Users/Jonathan/Documents/Programmering/8.semester/stochastic"
	},
	"version" : 
	{
		"major" : 2,
		"minor" : 7
	}
}
